{
	"format_version": "1.9.0",
	"credit": "Made by Dshbwlto",
	"texture_size": [512, 512],
	"textures": {
		"0": "createbionics:item/entity/organ_items",
		"particle": "createbionics:item/entity/organ_items"
	},
	"elements": [
		{
			"from": [1.5, 0, -6],
			"to": [14.5, 6.5, 22],
			"rotation": {"angle": 0, "axis": "y", "origin": [9.5, 99, -30]},
			"faces": {
				"north": {"uv": [3.4375, 9.98438, 3.84375, 10.1875], "texture": "#0"},
				"east": {"uv": [3.83906, 9.98438, 4.71406, 10.1875], "texture": "#0"},
				"south": {"uv": [3.4375, 9.98438, 3.84375, 10.1875], "texture": "#0"},
				"west": {"uv": [3.83906, 9.98438, 4.71406, 10.1875], "texture": "#0"},
				"up": {"uv": [3.84375, 9.98438, 3.4375, 9.10938], "texture": "#0"},
				"down": {"uv": [3.84375, 9.10938, 3.4375, 9.98438], "texture": "#0"}
			}
		},
		{
			"from": [3, 6.502, -9.25],
			"to": [13, 8.002, -4.25],
			"rotation": {"angle": 0, "axis": "y", "origin": [-2.5, 95.7, -76.7]},
			"faces": {
				"north": {"uv": [12.71875, 9.95313, 13.03125, 10], "texture": "#0"},
				"east": {"uv": [8.55078, 9.69141, 8.70703, 9.72266], "texture": "#0"},
				"south": {"uv": [12.71875, 9.95313, 13.03125, 10], "texture": "#0"},
				"west": {"uv": [9.01953, 9.69141, 9.17578, 9.72266], "texture": "#0"},
				"up": {"uv": [13.03125, 9.95313, 12.71875, 9.79688], "texture": "#0"},
				"down": {"uv": [13.03125, 9.79688, 12.71875, 9.95313], "texture": "#0"}
			}
		},
		{
			"from": [-1.25, 6.5, -5],
			"to": [17.25, 8, 25.5],
			"rotation": {"angle": 0, "axis": "y", "origin": [-9.75, 95.5, -15]},
			"faces": {
				"north": {"uv": [0.95313, 9.0625, 1.53125, 9.10938], "texture": "#0"},
				"east": {"uv": [0.01563, 9.0625, 0.95313, 9.10938], "texture": "#0"},
				"south": {"uv": [2.48438, 9.0625, 3.0625, 9.10938], "texture": "#0"},
				"west": {"uv": [1.53125, 9.0625, 2.46875, 9.10938], "texture": "#0"},
				"up": {"uv": [1.53125, 9.04688, 0.95313, 8.10938], "texture": "#0"},
				"down": {"uv": [1.53125, 8.10938, 0.95313, 9.04688], "texture": "#0"}
			}
		},
		{
			"from": [-1.5, 7, 24.5],
			"to": [17.5, 9, 26.5],
			"rotation": {"angle": 0, "axis": "y", "origin": [-9.75, 96, -16]},
			"faces": {
				"north": {"uv": [1.375, 6.9375, 1.96875, 7], "texture": "#0"},
				"east": {"uv": [1.3125, 6.9375, 1.375, 7], "texture": "#0"},
				"south": {"uv": [1.375, 6.9375, 1.96875, 7], "texture": "#0"},
				"west": {"uv": [1.3125, 6.9375, 1.375, 7], "texture": "#0"},
				"up": {"uv": [1.96875, 7, 1.375, 6.9375], "texture": "#0"},
				"down": {"uv": [1.96875, 6.9375, 1.375, 7], "texture": "#0"}
			}
		},
		{
			"from": [-1.25, 6.501, -5],
			"to": [4.75, 8.001, -0.5],
			"rotation": {"angle": 45, "axis": "y", "origin": [-1.25, 7, -5]},
			"faces": {
				"north": {"uv": [2.57813, 5.625, 2.76563, 5.67188], "texture": "#0"},
				"east": {"uv": [2.57813, 5.67188, 2.70313, 5.70313], "texture": "#0"},
				"south": {"uv": [2.57813, 5.625, 2.76563, 5.67188], "texture": "#0"},
				"west": {"uv": [2.57813, 5.67188, 2.70313, 5.70313], "texture": "#0"},
				"up": {"uv": [2.76563, 5.625, 2.57813, 5.5], "texture": "#0"},
				"down": {"uv": [2.76563, 5.5, 2.57813, 5.625], "texture": "#0"}
			}
		},
		{
			"from": [11.25, 6.501, -5],
			"to": [17.25, 8.001, -0.5],
			"rotation": {"angle": -45, "axis": "y", "origin": [17.25, 7, -5]},
			"faces": {
				"north": {"uv": [2.57813, 5.625, 2.76563, 5.67188], "texture": "#0"},
				"east": {"uv": [2.57813, 5.67188, 2.70313, 5.70313], "texture": "#0"},
				"south": {"uv": [2.57813, 5.625, 2.76563, 5.67188], "texture": "#0"},
				"west": {"uv": [2.57813, 5.67188, 2.70313, 5.70313], "texture": "#0"},
				"up": {"uv": [2.76563, 5.625, 2.57813, 5.5], "texture": "#0"},
				"down": {"uv": [2.76563, 5.5, 2.57813, 5.625], "texture": "#0"}
			}
		},
		{
			"from": [-1.25, 8, -5],
			"to": [17.25, 9.5, 25.5],
			"rotation": {"angle": 0, "axis": "y", "origin": [-9.75, 97, -15]},
			"faces": {
				"north": {"uv": [0.95313, 9.0625, 1.53125, 9.10938], "texture": "#0"},
				"east": {"uv": [0.01563, 9.0625, 0.95313, 9.10938], "texture": "#0"},
				"south": {"uv": [2.48438, 9.0625, 3.0625, 9.10938], "texture": "#0"},
				"west": {"uv": [1.53125, 9.0625, 2.46875, 9.10938], "texture": "#0"},
				"up": {"uv": [1.53125, 9.0625, 0.95313, 8.10938], "texture": "#0"},
				"down": {"uv": [1.53125, 8.10938, 0.95313, 9.0625], "texture": "#0"}
			}
		},
		{
			"from": [11.25, 8.001, -5],
			"to": [17.25, 9.501, -0.5],
			"rotation": {"angle": -45, "axis": "y", "origin": [17.25, 8.5, -5]},
			"faces": {
				"north": {"uv": [2.57813, 5.625, 2.76563, 5.67188], "texture": "#0"},
				"east": {"uv": [2.57813, 5.67188, 2.70313, 5.70313], "texture": "#0"},
				"south": {"uv": [2.57813, 5.625, 2.76563, 5.67188], "texture": "#0"},
				"west": {"uv": [2.57813, 5.67188, 2.70313, 5.70313], "texture": "#0"},
				"up": {"uv": [2.76563, 5.625, 2.57813, 5.5], "texture": "#0"},
				"down": {"uv": [2.76563, 5.5, 2.57813, 5.625], "texture": "#0"}
			}
		},
		{
			"from": [3, 8.002, -9.25],
			"to": [13, 9.502, -4.25],
			"rotation": {"angle": 0, "axis": "y", "origin": [-2.5, 97.2, -76.7]},
			"faces": {
				"north": {"uv": [12.71875, 9.95313, 13.03125, 10], "texture": "#0"},
				"east": {"uv": [8.55078, 9.69141, 8.70703, 9.72266], "texture": "#0"},
				"south": {"uv": [12.71875, 9.95313, 13.03125, 10], "texture": "#0"},
				"west": {"uv": [9.01953, 9.69141, 9.17578, 9.72266], "texture": "#0"},
				"up": {"uv": [13.03125, 9.95313, 12.71875, 9.79688], "texture": "#0"},
				"down": {"uv": [13.03125, 9.79688, 12.71875, 9.95313], "texture": "#0"}
			}
		},
		{
			"from": [-1.25, 8.001, -5],
			"to": [4.75, 9.501, -0.5],
			"rotation": {"angle": 45, "axis": "y", "origin": [-1.25, 8.5, -5]},
			"faces": {
				"north": {"uv": [2.57813, 5.625, 2.76563, 5.67188], "texture": "#0"},
				"east": {"uv": [2.57813, 5.67188, 2.70313, 5.70313], "texture": "#0"},
				"south": {"uv": [2.57813, 5.625, 2.76563, 5.67188], "texture": "#0"},
				"west": {"uv": [2.57813, 5.67188, 2.70313, 5.70313], "texture": "#0"},
				"up": {"uv": [2.76563, 5.625, 2.57813, 5.5], "texture": "#0"},
				"down": {"uv": [2.76563, 5.5, 2.57813, 5.625], "texture": "#0"}
			}
		}
	],
	"display": {
		"thirdperson_righthand": {
			"rotation": [-16, 0, 0],
			"scale": [0.5, 0.5, 0.5]
		},
		"thirdperson_lefthand": {
			"rotation": [-16, 0, 0],
			"scale": [0.5, 0.5, 0.5]
		},
		"firstperson_righthand": {
			"rotation": [-4, 0, 0],
			"scale": [0.5, 0.5, 0.5]
		},
		"firstperson_lefthand": {
			"rotation": [-4, 0, 0],
			"scale": [0.5, 0.5, 0.5]
		},
		"ground": {
			"translation": [0, 4.25, 0],
			"scale": [0.5, 0.5, 0.5]
		},
		"gui": {
			"rotation": [30, -135, 0],
			"translation": [1, 0, 0],
			"scale": [0.4, 0.4, 0.4]
		},
		"fixed": {
			"rotation": [-90, 0, 0],
			"translation": [0, 0, -6.75]
		}
	}
}