{
	"format_version": "1.9.0",
	"credit": "Made by Dshbwlto",
	"texture_size": [1024, 1024],
	"textures": {
		"1": "createbionics:item/entity/organ_items_1",
		"particle": "createbionics:item/entity/organ_items_1"
	},
	"elements": [
		{
			"name": "Whistle Large Base",
			"from": [-6, 0, -6],
			"to": [6, 2, 6],
			"faces": {
				"north": {"uv": [7.76563, 0.4375, 7.57813, 0.46875], "texture": "#1"},
				"east": {"uv": [7.95313, 0.4375, 7.76563, 0.46875], "texture": "#1"},
				"south": {"uv": [8.14063, 0.4375, 7.95313, 0.46875], "texture": "#1"},
				"west": {"uv": [7.57813, 0.4375, 7.39063, 0.46875], "texture": "#1"},
				"up": {"uv": [7.57813, 0.4375, 7.76563, 0.25], "texture": "#1"},
				"down": {"uv": [7.76563, 0.25, 7.95313, 0.4375], "texture": "#1"}
			}
		}
	]
}